linphone/avcodec-53.dll
linphone/avutil-51.dll
linphone/bzip2.dll
linphone/linphone.pyd
linphone/msvcp100.dll
linphone/msvcr100.dll
linphone/swresample-0.dll
linphone/swscale-2.dll
linphone/zlib.dll
linphone/__init__.py
linphone/share/images/nowebcamCIF.jpg
linphone/share/linphone/rootca.pem
linphone/share/sounds/linphone/hello16000.wav
linphone/share/sounds/linphone/hello8000.wav
linphone/share/sounds/linphone/incoming_chat.wav
linphone/share/sounds/linphone/ringback.wav
linphone/share/sounds/linphone/rings/bigben.wav
linphone/share/sounds/linphone/rings/oldphone-mono-30s.caf
linphone/share/sounds/linphone/rings/oldphone-mono.wav
linphone/share/sounds/linphone/rings/oldphone.wav
linphone/share/sounds/linphone/rings/orig.wav
linphone/share/sounds/linphone/rings/rock.wav
linphone/share/sounds/linphone/rings/sweet.wav
linphone/share/sounds/linphone/rings/synth.wav
linphone/share/sounds/linphone/rings/tapping.wav
linphone/share/sounds/linphone/rings/toy-mono.wav
linphone/unittests/linphonetester.py
linphone/unittests/README.txt
linphone/unittests/tester_hosts
linphone/unittests/test_call.py
linphone/unittests/test_message.py
linphone/unittests/test_presence.py
linphone/unittests/test_register.py
linphone/unittests/test_setup.py
linphone/unittests/certificates/altname/agent.pem
linphone/unittests/certificates/altname/cafile.pem
linphone/unittests/certificates/altname/openssl-altname.cnf
linphone/unittests/certificates/cn/agent.pem
linphone/unittests/certificates/cn/cafile.pem
linphone/unittests/certificates/cn/openssl-cn.cnf
linphone/unittests/images/nowebcamCIF.jpg
linphone/unittests/rcfiles/empty_rc
linphone/unittests/rcfiles/laure_call_logs_rc
linphone/unittests/rcfiles/laure_rc
linphone/unittests/rcfiles/marie_early_rc
linphone/unittests/rcfiles/marie_h264_rc
linphone/unittests/rcfiles/marie_quality_reporting_rc
linphone/unittests/rcfiles/marie_rc
linphone/unittests/rcfiles/marie_rc_rtcp_xr
linphone-3.9.1.dist-info/DESCRIPTION.rst
linphone-3.9.1.dist-info/METADATA
linphone-3.9.1.dist-info/metadata.json
linphone-3.9.1.dist-info/RECORD
linphone-3.9.1.dist-info/top_level.txt
linphone-3.9.1.dist-info/WHEEL
linphone-3.9.1.dist-info/zip-safe
